fits2db/__init__.py
fits2db/log.py
fits2db/adapters/__init__.py
fits2db/adapters/base.py
fits2db/adapters/meta.py
fits2db/adapters/mysql.py
fits2db/cli/__init__.py
fits2db/cli/cli.py
fits2db/cli/helper_func.py
fits2db/cli/utils.py
fits2db/config/__init__.py
fits2db/config/config.py
fits2db/config/config_model.py
fits2db/config/templates/config.yaml.j2
fits2db/core/__init__.py
fits2db/core/core.py
fits2db/fits/__init__.py
fits2db/fits/fits.py
plots/TSI_PLOT_LIB_JTSIM_pandas.py
plots/anual_HKplot_DATA_JTSIM_DB.py
plots/custom_HKplot_DATA_JTSIM_DB.py
plots/dailyHKplot_DATA_JTSIM_DB.py
plots/irradiancePlot_DATA_JTSIM_DB.py
plots/lifetime_HKplot_DATA_JTSIM_DB.py
plots/monthly_HKplot_DATA_JTSIM_DB.py
plots/plot_data.py
plots/requirements.txt
tests/__init__.py
tests/integration/__init__.py
tests/integration/mysql/__init__.py
tests/integration/mysql/test_mysql_db.py
tests/integration/mysql/base/__init__.py
tests/integration/mysql/base/test_base.py
tests/unit/__init__.py
tests/unit/test_config.py
tests/unit/test_config_model.py
tests/unit/test_core.py
tests/unit/test_fits_class.py
tests/unit/test_fits_table.py
tests/unit/data/2021-07-07_L1a.txt
fits2db-0.1.0.dist-info/LICENSE
fits2db-0.1.0.dist-info/METADATA
fits2db-0.1.0.dist-info/WHEEL
fits2db-0.1.0.dist-info/entry_points.txt
fits2db-0.1.0.dist-info/top_level.txt
fits2db-0.1.0.dist-info/RECORD
