Metadata-Version: 2.1
Name: fits2db
Version: 0.1.0
Summary: A cli tool to load and manage tables from fits files into a sql database
Author-email: Cédric Renda <cedric.renda@hotmail.com>
Project-URL: Repository, https://github.com/pmodwrc/fits2db
Project-URL: Documentation, https://pmodwrc.github.io/fits2db/
Project-URL: Issues, https://github.com/pmodwrc/fits2db/issues
Classifier: Programming Language :: Python :: 3
Classifier: License :: OSI Approved :: MIT License
Classifier: Operating System :: OS Independent
Classifier: Development Status :: 3 - Alpha
Classifier: Intended Audience :: Developers
Classifier: Intended Audience :: End Users/Desktop
Classifier: Intended Audience :: Science/Research
Classifier: Natural Language :: English
Classifier: Operating System :: Unix
Classifier: Operating System :: POSIX :: Linux
Classifier: Operating System :: MacOS
Classifier: Programming Language :: Python
Classifier: Programming Language :: Python :: 3.9
Classifier: Programming Language :: Python :: 3.10
Classifier: Programming Language :: Python :: 3.11
Classifier: Programming Language :: Python :: 3.12
Classifier: Topic :: Software Development
Classifier: Topic :: Software Development :: Libraries :: Python Modules
Classifier: Topic :: System :: Software Distribution
Classifier: Typing :: Typed
Requires-Python: >=3.9
License-File: LICENSE
Requires-Dist: pandas>=2.0
Requires-Dist: pydantic>=2.8.0
Requires-Dist: Jinja2>=2.5.0
Requires-Dist: astropy>=6.0.0
Requires-Dist: numpy<2.0,>=1.0.0
Requires-Dist: sqlalchemy>=2.0.0
Requires-Dist: tqdm>=4.0.0
Requires-Dist: mysql-connector-python>=8.0.0
Requires-Dist: click>=8.1.7
